<?xml version="1.0" encoding="UTF-8"?>

<xwikidoc>
<web>MultiPageExport</web>
<name>ExportSheet2</name>
<language></language>
<defaultLanguage></defaultLanguage>
<translation>0</translation>
<parent>MultiPageExport.WebHome</parent>
<creator>xwiki:XWiki.Admin</creator>
<author>xwiki:XWiki.Admin</author>
<customClass></customClass>
<contentAuthor>xwiki:XWiki.Admin</contentAuthor>
<creationDate>1241084731000</creationDate>
<date>1255885549000</date>
<contentUpdateDate>1255885549000</contentUpdateDate>
<version>1.1</version>
<title></title>
<template></template>
<defaultTemplate></defaultTemplate>
<validationScript></validationScript>
<comment></comment>
<minorEdit>false</minorEdit>
<syntaxId>xwiki/1.0</syntaxId>
<hidden>false</hidden>
<object>
<class>
<name>XWiki.TagClass</name>
<customClass></customClass>
<customMapping></customMapping>
<defaultViewSheet></defaultViewSheet>
<defaultEditSheet></defaultEditSheet>
<defaultWeb></defaultWeb>
<nameField></nameField>
<validationScript></validationScript>
<tags>
<cache>0</cache>
<displayType>checkbox</displayType>
<multiSelect>1</multiSelect>
<name>tags</name>
<number>1</number>
<prettyName>Tags</prettyName>
<relationalStorage>1</relationalStorage>
<separator> </separator>
<separators> ,|</separators>
<size>30</size>
<unmodifiable>0</unmodifiable>
<values></values>
<classType>com.xpn.xwiki.objects.classes.StaticListClass</classType>
</tags>
</class>
<name>MultiPageExport.ExportSheet2</name>
<number>0</number>
<className>XWiki.TagClass</className>
<guid>e4ac8468-eafd-4f86-8e05-81a6dbc03613</guid>
<property>
<tags/>
</property>
</object>
<content>#set($cplugin = $xwiki.collection)
#if($request.page)
#set($docName = $request.page)
#else
#set($docName = $doc.fullName)
#end
#set($packageDoc = $xwiki.getDocument($docName))
#set($packageDocName = $xwiki.clearName($packageDoc.getDisplayTitle()))
#if($request.type)
## real export
#if($request.type=="view")
{pre}
$cplugin.getRenderedContentWithLinks($docName)
{/pre}
#else
#if($request.packagename=="")
#set($packagename = "export")
#else
#set($packagename = $request.packagename)
#end
#set($pdfpages = $request.pdfpages)
#set($selectlist = $cplugin.split($pdfpages, "|"))
#set($ok = $selectlist.remove(""))
#if($request.type=="html")
{pre}
$cplugin.getRenderedContentWithLinks($docName, $selectlist)
{/pre}
#elseif($request.type=="xarwithversions")
$response.setContentType("application/zip");
$response.addHeader("Content-disposition", "inline; filename=${packagename}.xar");
$cplugin.exportToXAR($packagename, $selectlist, true)
$context.setFinished(true)
#elseif($request.type=="xarwithoutversions")
$response.setContentType("application/zip");
$response.addHeader("Content-disposition", "inline; filename=${packagename}.xar");
$cplugin.exportToXAR($packagename, $selectlist, false)
$context.setFinished(true)
#elseif($request.type=="pdf")
## direct PDF generation
$cplugin.exportWithLinks($packagename, $docName, $selectlist, "pdf")
$context.setFinished(true)
#elseif($request.type=="rtf")
## direct RTF generation
$cplugin.exportWithLinks($packagename, $docName, $selectlist, "rtf")
$context.setFinished(true)
#else
{pre}
$cplugin.getRenderedContentWithLinks($docName, $selectlist)
{/pre}
#end
#end
#elseif($request.pdfpages)
#set($pdfpages = $request.pdfpages)
#set($selectlist = $cplugin.split($pdfpages, "|"))
&lt;div class="export_to_print_box"&gt;
1 $msg.export_exportorprint_title

$msg.export_exportorprint_description :
#foreach($page in $selectlist)
#set($pageDoc = $xwiki.getDocument($page))
#if($page!="")
* $pageDoc.getDisplayTitle() ($page)
#end
#end
#if($request.page)
#set($printurl = $xwiki.getURL($request.page, "view", "xpage=printmulti&amp;bc=$!{request.pagebc}"))
#else
#set($printurl = $xwiki.getURL("MultiPageExport.Print", "view", "xpage=print&amp;bc=$!{request.pagebc}"))
#end
#set($printurljs = $cplugin.escapeForJS($printurl))
&lt;div class="export_to_print_buttons"&gt;
&lt;form name="export" action="$printurl" method="POST"&gt;
&lt;input type="hidden" name="page" value="$!{request.page}" /&gt;
&lt;input type="hidden" name="pdfpages" value="${pdfpages}" /&gt;
&lt;input type="hidden" name="xpage" value="" /&gt;
$msg.export_exportorprint_packagename &lt;input type="text" name="packagename" size="40" value="${packageDocName}" /&gt;
&lt;br /&gt;
&lt;input type="radio" name="type" value="html" checked onclick="this.form.action='${printurljs}'; this.form.xpage.value='print';" /&gt; $msg.export_exportorprint_HTML
&lt;input type="radio" name="type" value="pdf"  onclick="this.form.action='Export'; this.form.xpage.value='';" /&gt; $msg.export_exportorprint_PDF
##&lt;input type="radio" name="type" value="rtf" onclick="this.form.action='Export'; this.form.xpage.value='';" /&gt; $msg.export_exportorprint_RTF
&lt;input type="radio" name="type" value="xarwithversions" onclick="this.form.action='Export'; this.form.xpage.value='';" /&gt; $msg.export_exportorprint_XARWITHVERSIONS
&lt;input type="radio" name="type" value="xarwithoutversions" onclick="this.form.action='Export'; this.form.xpage.value='';" /&gt; $msg.export_exportorprint_XARWITHOUTVERSIONS
&lt;br /&gt;
&lt;span class="buttonwrapper"&gt;&lt;input type="submit" value="$msg.export_exportorprint_button_export" /&gt;&lt;/span&gt;
&lt;/form&gt;
&lt;/div&gt;
&lt;/div&gt;
#else
&lt;div class="export_to_print_box"&gt;
1 $msg.export_exportorprint_title

$msg.export_exportorprint_description :
{pre}
&lt;form action="" method="POST"&gt;
#set($pdfpages = "")
#set($treelist = $cplugin.getLinksTreeList($docName))
#set($selectlist = $xwiki.arrayList)
#foreach($treeitem in $treelist)
#set($ok = $selectlist.add($treeitem.id))
#set($pdfpages = "${pdfpages}|${treeitem.id}")
#end
#if($request.debug=="1")
#end
#set($fieldname = "pdfpages")
#set($tree = $xwiki.parseTemplate("treeview.vm"))
$tree
&lt;div class="export_to_print_buttons"&gt;
&lt;input type="hidden" name="action" value="export" /&gt;
&lt;input type="hidden" name="page" value="$!{request.page}" /&gt;
&lt;input type="hidden" id="pdfpages" name="pdfpages" value="${pdfpages}" /&gt;
&lt;span class="buttonwrapper"&gt;&lt;input type="submit" value="$msg.export_exportorprint_button_next" /&gt;&lt;/span&gt;
&lt;/div&gt;
&lt;/form&gt;
{/pre}
&lt;/div&gt;
#end
#if($request.debug=="1")
&lt;div class="debug"&gt;
Debug: $cplugin.getDebug()
&lt;/div&gt;
#end</content>
</xwikidoc>
